AmendmentBackUp/AmendmentBackUp.py
AmendmentBackUp/__init__.py
AmendmentBackUp/createDemo.py
AmendmentBackUp/createFile.py
amendment_back_up-0.1.5.dist-info/DESCRIPTION.rst
amendment_back_up-0.1.5.dist-info/METADATA
amendment_back_up-0.1.5.dist-info/RECORD
amendment_back_up-0.1.5.dist-info/WHEEL
amendment_back_up-0.1.5.dist-info/metadata.json
amendment_back_up-0.1.5.dist-info/top_level.txt
